{"rss": {"channel": {"item": [{"title": "MVC-FIRE ONLY", "link": "http://maps.google.com/maps?q=29.521631,-98.465319", "guid": {"@isPermaLink": "false", "#text": "29.521631,-98.465319"}, "description": "2000 Sable Ln | SAFD | 01:15:05", "pubDate": "Thu, 11 Dec 2025 01:15:05 CDT", "active_status": "no"}, {"title": "MVC-FIRE ONLY", "link": "http://maps.google.com/maps?q=44.242364,-119.809302", "guid": {"@isPermaLink": "false", "#text": "44.242364,-119.809302"}, "description": "9898-10298 Bandera Rd | SAFD | 01:20:10", "pubDate": "Thu, 11 Dec 2025 01:20:10 CDT", "active_status": "yes"}, {"title": "MVC-FIRE ONLY", "link": "http://maps.google.com/maps?q=29.537043,-98.651003", "guid": {"@isPermaLink": "false", "#text": "29.537043,-98.651003"}, "description": "9898-10298 Bandera Rd | SAFD | 01:25:06", "pubDate": "Thu, 11 Dec 2025 01:25:06 CDT", "active_status": "no"}, {"title": "GRASS/BRUSH FIRE", "link": "http://maps.google.com/maps?q=29.424284,-98.506557", "guid": {"@isPermaLink": "false", "#text": "29.424284,-98.506557"}, "description": "300-314 S Frio St | SAFD | 03:15:05", "pubDate": "Thu, 11 Dec 2025 03:15:05 CDT", "active_status": "no"}, {"title": "MVC-FIRE ONLY", "link": "http://maps.google.com/maps?q=29.371171,-98.475223", "guid": {"@isPermaLink": "false", "#text": "29.371171,-98.475223"}, "description": "Vfw Blvd / S Presa St | SAFD | 06:20:05", "pubDate": "Thu, 11 Dec 2025 06:20:05 CDT", "active_status": "no"}, {"title": "GRASS/BRUSH FIRE", "link": "http://maps.google.com/maps?q=29.354603,-98.518853", "guid": {"@isPermaLink": "false", "#text": "29.354603,-98.518853"}, "description": "Commercial Ave / Grosvenor Blvd | SAFD | 06:55:05", "pubDate": "Thu, 11 Dec 2025 06:55:05 CDT", "active_status": "no"}, {"title": "MVC-FIRE ONLY", "link": "http://maps.google.com/maps?q=29.450138,-98.629103", "guid": {"@isPermaLink": "false", "#text": "29.450138,-98.629103"}, "description": "6952-7067 CULEBRA RD | SAFD | 07:10:05", "pubDate": "Thu, 11 Dec 2025 07:10:05 CDT", "active_status": "no"}, {"title": "BRUSH/GRASS FIRE", "link": "http://maps.google.com/maps?q=29.435692,-98.713200", "guid": {"@isPermaLink": "false", "#text": "29.435692,-98.713200"}, "description": "Loop 1604 N | SAFD | 07:25:09", "pubDate": "Thu, 11 Dec 2025 07:25:09 CDT", "active_status": "no"}, {"title": "MVC-FIRE ONLY", "link": "http://maps.google.com/maps?q=29.531387,-98.483781", "guid": {"@isPermaLink": "false", "#text": "29.531387,-98.483781"}, "description": "9800 Airport Blvd | SAFD | 07:35:05", "pubDate": "Thu, 11 Dec 2025 07:35:05 CDT", "active_status": "no"}, {"title": "UNAUTH BURNING", "link": "http://maps.google.com/maps?q=29.489081,-98.537538", "guid": {"@isPermaLink": "false", "#text": "29.489081,-98.537538"}, "description": "1800 Vance Jackson | SAFD | 07:50:05", "pubDate": "Thu, 11 Dec 2025 07:50:05 CDT", "active_status": "no"}, {"title": "VEHICLE FIRE", "link": "http://maps.google.com/maps?q=29.359501,-98.549902", "guid": {"@isPermaLink": "false", "#text": "29.359501,-98.549902"}, "description": "Somerset Rd / Price Ave | SAFD | 08:25:05", "pubDate": "Thu, 11 Dec 2025 08:25:05 CDT", "active_status": "no"}, {"title": "MVC-FIRE ONLY", "link": "http://maps.google.com/maps?q=29.347528,-98.553809", "guid": {"@isPermaLink": "false", "#text": "29.347528,-98.553809"}, "description": "W HUTCHINS PLACE / IH 35 S | SAFD | 08:25:06", "pubDate": "Thu, 11 Dec 2025 08:25:06 CDT", "active_status": "no"}, {"title": "FIRE-REPORT-ONLY", "link": "http://maps.google.com/maps?q=29.529942,-98.406014", "guid": {"@isPermaLink": "false", "#text": "29.529942,-98.406014"}, "description": "4500 Longvale Dr | SAFD | 08:25:06", "pubDate": "Thu, 11 Dec 2025 08:25:06 CDT", "active_status": "no"}, {"title": "VEHICLE FIRE", "link": "http://maps.google.com/maps?q=29.481070,-98.357637", "guid": {"@isPermaLink": "false", "#text": "29.481070,-98.357637"}, "description": "W0 Ih 10 E Ofrp Fm 1516 N | SAFD | 08:30:06", "pubDate": "Thu, 11 Dec 2025 08:30:06 CDT", "active_status": "no"}, {"title": "MVC-FIRE ONLY", "link": "http://maps.google.com/maps?q=29.518188,-98.452666", "guid": {"@isPermaLink": "false", "#text": "29.518188,-98.452666"}, "description": "Nacogdoches Rd / Blossom Dr | SAFD | 09:10:05", "pubDate": "Thu, 11 Dec 2025 09:10:05 CDT", "active_status": "no"}, {"title": "UNAUTH BURNING", "link": "http://maps.google.com/maps?q=29.468841,-98.501992", "guid": {"@isPermaLink": "false", "#text": "29.468841,-98.501992"}, "description": "400-411 Elmwood | SAFD | 09:20:08", "pubDate": "Thu, 11 Dec 2025 09:20:08 CDT", "active_status": "no"}, {"title": "UNAUTH BURNING", "link": "http://maps.google.com/maps?q=29.427590,-98.535338", "guid": {"@isPermaLink": "false", "#text": "29.427590,-98.535338"}, "description": "3100 Buena Vista St | SAFD | 09:20:09", "pubDate": "Thu, 11 Dec 2025 09:20:09 CDT", "active_status": "no"}, {"title": "UNAUTH BURNING", "link": "http://maps.google.com/maps?q=29.441592,-98.525632", "guid": {"@isPermaLink": "false", "#text": "29.441592,-98.525632"}, "description": "1000 Menchaca St | SAFD | 09:45:05", "pubDate": "Thu, 11 Dec 2025 09:45:05 CDT", "active_status": "no"}, {"title": "MVC-FIRE ONLY", "link": "http://maps.google.com/maps?q=29.470615,-98.506888", "guid": {"@isPermaLink": "false", "#text": "29.470615,-98.506888"}, "description": "W Olmos Dr / Beacon Ave | SAFD | 09:55:05", "pubDate": "Thu, 11 Dec 2025 09:55:05 CDT", "active_status": "no"}, {"title": "UNAUTH BURNING", "link": "http://maps.google.com/maps?q=29.445808,-98.534469", "guid": {"@isPermaLink": "false", "#text": "29.445808,-98.534469"}, "description": "1400 Culebra Rd | SAFD | 10:00:05", "pubDate": "Thu, 11 Dec 2025 10:00:05 CDT", "active_status": "no"}, {"title": "BRUSH/GRASS FIRE", "link": "http://maps.google.com/maps?q=29.373501,-98.463787", "guid": {"@isPermaLink": "false", "#text": "29.373501,-98.463787"}, "description": "N0 Ih 37 S Onrp Wb Ih 10 E | SAFD | 11:30:09", "pubDate": "Thu, 11 Dec 2025 11:30:09 CDT", "active_status": "no"}, {"title": "MVC-FIRE ONLY", "link": "http://maps.google.com/maps?q=29.473586,-98.674066", "guid": {"@isPermaLink": "false", "#text": "29.473586,-98.674066"}, "description": "Westover Hills Blvd / Raba Dr | SAFD | 12:00:15", "pubDate": "Thu, 11 Dec 2025 12:00:15 CDT", "active_status": "no"}, {"title": "MVC-FIRE ONLY", "link": "http://maps.google.com/maps?q=29.525338,-98.558340", "guid": {"@isPermaLink": "false", "#text": "29.525338,-98.558340"}, "description": "9500 Tioga Dr | SAFD | 12:05:07", "pubDate": "Thu, 11 Dec 2025 12:05:07 CDT", "active_status": "no"}, {"title": "BRUSH/GRASS FIRE", "link": "http://maps.google.com/maps?q=29.439822,-98.532915", "guid": {"@isPermaLink": "false", "#text": "29.439822,-98.532915"}, "description": "S0 Ih 37 S Ofrp Military Dr | SAFD | 12:35:07", "pubDate": "Thu, 11 Dec 2025 12:35:07 CDT", "active_status": "no"}, {"title": "GRASS/BRUSH FIRE", "link": "http://maps.google.com/maps?q=29.321031,-98.520186", "guid": {"@isPermaLink": "false", "#text": "29.321031,-98.520186"}, "description": "923-1299 W Chavaneaux Rd | SAFD | 13:05:06", "pubDate": "Thu, 11 Dec 2025 13:05:06 CDT", "active_status": "no"}, {"title": "VEHICLE FIRE", "link": "http://maps.google.com/maps?q=29.547696,-98.669717", "guid": {"@isPermaLink": "false", "#text": "29.547696,-98.669717"}, "description": "10900-10999 Stonecroft | SAFD | 13:20:07", "pubDate": "Thu, 11 Dec 2025 13:20:07 CDT", "active_status": "no"}, {"title": "MVC-FIRE ONLY", "link": "http://maps.google.com/maps?q=29.567110,-98.388969", "guid": {"@isPermaLink": "false", "#text": "29.567110,-98.388969"}, "description": "O'connor Rd / Nacogdoches Rd | SAFD | 13:25:09", "pubDate": "Thu, 11 Dec 2025 13:25:09 CDT", "active_status": "no"}, {"title": "UNAUTH BURNING", "link": "http://maps.google.com/maps?q=29.517301,-98.453109", "guid": {"@isPermaLink": "false", "#text": "29.517301,-98.453109"}, "description": "1200 Ne Loop 410 | SAFD | 13:50:05", "pubDate": "Thu, 11 Dec 2025 13:50:05 CDT", "active_status": "no"}, {"title": "MVC-FIRE ONLY", "link": "http://maps.google.com/maps?q=29.490726,-98.537611", "guid": {"@isPermaLink": "false", "#text": "29.490726,-98.537611"}, "description": "Freiling Dr / Vance Jackson Rd | SAFD | 14:25:08", "pubDate": "Thu, 11 Dec 2025 14:25:08 CDT", "active_status": "no"}, {"title": "MVC-FIRE ONLY", "link": "http://maps.google.com/maps?q=29.331176,-98.500147", "guid": {"@isPermaLink": "false", "#text": "29.331176,-98.500147"}, "description": "9200 Walhalla Ave | SAFD | 14:25:08", "pubDate": "Thu, 11 Dec 2025 14:25:08 CDT", "active_status": "no"}]}}}