{"rss": {"channel": {"item": [{"title": "FIRE EVENT", "link": "http://maps.google.com/maps?q=29.848721,-95.332733", "guid": {"@isPermaLink": "false", "#text": "29.848721,-95.332733"}, "description": "TIDWELL RD | HFD | 00:00:07", "pubDate": "Fri, 02 Aug 2024 00:00:07 CDT", "active_status": "yes"}, {"title": "FIRE EVENT", "link": "http://maps.google.com/maps?q=29.769406,-95.47121", "guid": {"@isPermaLink": "false", "#text": "29.769406,-95.47121"}, "description": "PINE BRIAR CIR | HFD | 00:00:07", "pubDate": "Fri, 02 Aug 2024 00:00:07 CDT", "active_status": "no"}, {"title": "FIRE EVENT", "link": "http://maps.google.com/maps?q=29.863561,-95.396935", "guid": {"@isPermaLink": "false", "#text": "29.863561,-95.396935"}, "description": "E ECHO GLEN DR | HFD | 00:05:05", "pubDate": "Fri, 02 Aug 2024 00:05:05 CDT", "active_status": "no"}, {"title": "FIRE EVENT", "link": "http://maps.google.com/maps?q=29.806085,-95.286252", "guid": {"@isPermaLink": "false", "#text": "29.806085,-95.286252"}, "description": "PARDEE ST | HFD | 00:15:09", "pubDate": "Fri, 02 Aug 2024 00:15:09 CDT", "active_status": "no"}, {"title": "FIRE EVENT", "link": "http://maps.google.com/maps?q=29.73236,-95.512252", "guid": {"@isPermaLink": "false", "#text": "29.73236,-95.512252"}, "description": "BOULDER RANCH DR | HFD | 01:00:11", "pubDate": "Fri, 02 Aug 2024 01:00:11 CDT", "active_status": "yes"}]}}}