{"rss": {"channel": {"item": [{"title": "211 fire", "link": "http://maps.google.com/maps?q=29.733686,-95.608428", "guid": {"@isPermaLink": "false", "#text": "29.733686,-95.608428"}, "description": "ASHFORD MEADOW DR | HFD | 00:00:06", "pubDate": "Mon, 21 Aug 2023 00:00:06 CDT", "active_status": "no"}, {"title": "Car Fire", "link": "http://maps.google.com/maps?q=29.932467,-95.299675", "guid": {"@isPermaLink": "false", "#text": "29.932467,-95.299675"}, "description": "EASTEX FWY IB | HFD | 00:00:06", "pubDate": "Mon, 21 Aug 2023 00:00:06 CDT", "active_status": "no"}, {"title": "Fire Event", "link": "http://maps.google.com/maps?q=29.816714,-95.535158", "guid": {"@isPermaLink": "false", "#text": "29.816714,-95.535158"}, "description": "PARANA DR | HFD | 00:20:06", "pubDate": "Mon, 21 Aug 2023 00:20:06 CDT", "active_status": "no"}, {"title": "Fire Event", "link": "http://maps.google.com/maps?q=29.815312,-95.526223", "guid": {"@isPermaLink": "false", "#text": "29.815312,-95.526223"}, "description": "CAMPBELL RD | HFD | 00:20:06", "pubDate": "Mon, 21 Aug 2023 00:20:06 CDT", "active_status": "no"}, {"title": "Fire Event", "link": "http://maps.google.com/maps?q=29.733981,-95.489823", "guid": {"@isPermaLink": "false", "#text": "29.733981,-95.489823"}, "description": "GREENRIDGE DR | HFD | 01:10:07", "pubDate": "Mon, 21 Aug 2023 01:10:07 CDT", "active_status": "no"}, {"title": "Fire Event", "link": "http://maps.google.com/maps?q=29.805869,-95.489384", "guid": {"@isPermaLink": "false", "#text": "29.805869,-95.489384"}, "description": "AMELIA RD | HFD | 01:10:07", "pubDate": "Mon, 21 Aug 2023 01:10:07 CDT", "active_status": "no"}, {"title": "Building Fire", "link": "http://maps.google.com/maps?q=29.674677,-95.336403", "guid": {"@isPermaLink": "false", "#text": "29.674677,-95.336403"}, "description": "MARTIN LUTHER KING BLVD  | HFD | 02:10:09", "pubDate": "Mon, 21 Aug 2023 02:10:09 CDT", "active_status": "no"}, {"title": "Fire Event", "link": "http://maps.google.com/maps?q=29.742303,-95.53839", "guid": {"@isPermaLink": "false", "#text": "29.742303,-95.53839"}, "description": "S GESSNER RD | HFD | 02:30:07", "pubDate": "Mon, 21 Aug 2023 02:30:07 CDT", "active_status": "no"}, {"title": "Building Fire", "link": "http://maps.google.com/maps?q=29.675268,-95.336439", "guid": {"@isPermaLink": "false", "#text": "29.675268,-95.336439"}, "description": "MARTIN LUTHER KING BLVD | HFD | 02:45:04", "pubDate": "Mon, 21 Aug 2023 02:45:04 CDT", "active_status": "no"}, {"title": "Trash Fire", "link": "http://maps.google.com/maps?q=29.73098,-95.409688", "guid": {"@isPermaLink": "false", "#text": "29.73098,-95.409688"}, "description": "SUS59OB-SHEPHERD DR S S US 59 FWY OB | HFD | 03:30:04", "pubDate": "Mon, 21 Aug 2023 03:30:04 CDT", "active_status": "no"}, {"title": "Fire Event", "link": "http://maps.google.com/maps?q=29.689459,-95.561335", "guid": {"@isPermaLink": "false", "#text": "29.689459,-95.561335"}, "description": "BEECHNUT ST | HFD | 06:15:05", "pubDate": "Mon, 21 Aug 2023 06:15:05 CDT", "active_status": "no"}, {"title": "Fire Event", "link": "http://maps.google.com/maps?q=29.73715,-95.460642", "guid": {"@isPermaLink": "false", "#text": "29.73715,-95.460642"}, "description": "POST OAK BLVD | HFD | 06:25:04", "pubDate": "Mon, 21 Aug 2023 06:25:04 CDT", "active_status": "no"}, {"title": "Fire Event", "link": "http://maps.google.com/maps?q=29.697465,-95.331514", "guid": {"@isPermaLink": "false", "#text": "29.697465,-95.331514"}, "description": "ROYAL PALMS ST | HFD | 06:25:04", "pubDate": "Mon, 21 Aug 2023 06:25:04 CDT", "active_status": "no"}, {"title": "Apartment Fire", "link": "http://maps.google.com/maps?q=29.732424,-95.653268", "guid": {"@isPermaLink": "false", "#text": "29.732424,-95.653268"}, "description": "RICHMOND AVE | HFD | 06:30:06", "pubDate": "Mon, 21 Aug 2023 06:30:06 CDT", "active_status": "no"}, {"title": "Fire Event", "link": "http://maps.google.com/maps?q=29.783548,-95.446371", "guid": {"@isPermaLink": "false", "#text": "29.783548,-95.446371"}, "description": "OLD KATY RD | HFD | 06:30:06", "pubDate": "Mon, 21 Aug 2023 06:30:06 CDT", "active_status": "no"}, {"title": "Apartment Fire", "link": "http://maps.google.com/maps?q=29.947988,-95.397682", "guid": {"@isPermaLink": "false", "#text": "29.947988,-95.397682"}, "description": "IMPERIAL VALLEY DR | HFD | 07:20:06", "pubDate": "Mon, 21 Aug 2023 07:20:06 CDT", "active_status": "no"}, {"title": "Fire Event", "link": "http://maps.google.com/maps?q=29.75222,-95.368577", "guid": {"@isPermaLink": "false", "#text": "29.75222,-95.368577"}, "description": "MAIN ST | HFD | 07:55:05", "pubDate": "Mon, 21 Aug 2023 07:55:05 CDT", "active_status": "no"}, {"title": "Fire Event", "link": "http://maps.google.com/maps?q=29.778375,-95.350538", "guid": {"@isPermaLink": "false", "#text": "29.778375,-95.350538"}, "description": "LORRAINE ST  | HFD | 08:15:05", "pubDate": "Mon, 21 Aug 2023 08:15:05 CDT", "active_status": "no"}, {"title": "Fire Event", "link": "http://maps.google.com/maps?q=29.633782,-95.411561", "guid": {"@isPermaLink": "false", "#text": "29.633782,-95.411561"}, "description": "ALMEDA RD | HFD | 08:15:05", "pubDate": "Mon, 21 Aug 2023 08:15:05 CDT", "active_status": "no"}, {"title": "House on Fire", "link": "http://maps.google.com/maps?q=29.76549,-95.206993", "guid": {"@isPermaLink": "false", "#text": "29.76549,-95.206993"}, "description": "BERTHAS LN | HFD | 08:25:05", "pubDate": "Mon, 21 Aug 2023 08:25:05 CDT", "active_status": "no"}, {"title": "Fire Event", "link": "http://maps.google.com/maps?q=29.717903,-95.311726", "guid": {"@isPermaLink": "false", "#text": "29.717903,-95.311726"}, "description": "SYLVAN RD | HFD | 08:25:05", "pubDate": "Mon, 21 Aug 2023 08:25:05 CDT", "active_status": "no"}, {"title": "Fire Event", "link": "http://maps.google.com/maps?q=29.656072,-95.503407", "guid": {"@isPermaLink": "false", "#text": "29.656072,-95.503407"}, "description": "W BELLFORT AVE | HFD | 08:40:05", "pubDate": "Mon, 21 Aug 2023 08:40:05 CDT", "active_status": "no"}, {"title": "Fire Event", "link": "http://maps.google.com/maps?q=29.712914,-95.374978", "guid": {"@isPermaLink": "false", "#text": "29.712914,-95.374978"}, "description": "S MACGREGOR WAY | HFD | 08:50:05", "pubDate": "Mon, 21 Aug 2023 08:50:05 CDT", "active_status": "no"}, {"title": "Building Fire", "link": "http://maps.google.com/maps?q=29.753122,-95.403744", "guid": {"@isPermaLink": "false", "#text": "29.753122,-95.403744"}, "description": "W GRAY ST | HFD | 09:10:06", "pubDate": "Mon, 21 Aug 2023 09:10:06 CDT", "active_status": "no"}, {"title": "Building Fire", "link": "http://maps.google.com/maps?q=29.758453,-95.367575", "guid": {"@isPermaLink": "false", "#text": "29.758453,-95.367575"}, "description": "LOUISIANA ST | HFD | 09:30:05", "pubDate": "Mon, 21 Aug 2023 09:30:05 CDT", "active_status": "no"}, {"title": "Fire Event", "link": "http://maps.google.com/maps?q=29.71983,-95.603849", "guid": {"@isPermaLink": "false", "#text": "29.71983,-95.603849"}, "description": " ASHFORD POINT DR | HFD | 09:30:05", "pubDate": "Mon, 21 Aug 2023 09:30:05 CDT", "active_status": "no"}, {"title": "Grass Fire", "link": "http://maps.google.com/maps?q=29.800438,-95.286618", "guid": {"@isPermaLink": "false", "#text": "29.800438,-95.286618"}, "description": "LIBERTY RD | HFD | 09:55:04", "pubDate": "Mon, 21 Aug 2023 09:55:04 CDT", "active_status": "no"}, {"title": "Trash Fire", "link": "http://maps.google.com/maps?q=29.726193,-95.460769", "guid": {"@isPermaLink": "false", "#text": "29.726193,-95.460769"}, "description": "SOUTHWEST FWY ENTR  | HFD | 10:10:05", "pubDate": "Mon, 21 Aug 2023 10:10:05 CDT", "active_status": "no"}, {"title": "Car Fire", "link": "http://maps.google.com/maps?q=29.863578,-95.430878", "guid": {"@isPermaLink": "false", "#text": "29.863578,-95.430878"}, "description": "TC ACRES HOMES W LITTLE YORK RD | HFD | 10:55:04", "pubDate": "Mon, 21 Aug 2023 10:55:04 CDT", "active_status": "no"}, {"title": "Grass Fire", "link": "http://maps.google.com/maps?q=29.852642,-95.262367", "guid": {"@isPermaLink": "false", "#text": "29.852642,-95.262367"}, "description": "MESA DR | HFD | 11:15:06", "pubDate": "Mon, 21 Aug 2023 11:15:06 CDT", "active_status": "no"}, {"title": "Fire Event", "link": "http://maps.google.com/maps?q=29.883249,-95.294265", "guid": {"@isPermaLink": "false", "#text": "29.883249,-95.294265"}, "description": "GUADALUPE ST | HFD | 11:25:04", "pubDate": "Mon, 21 Aug 2023 11:25:04 CDT", "active_status": "no"}, {"title": "Tree on Fire", "link": "http://maps.google.com/maps?q=29.627601,-95.23823", "guid": {"@isPermaLink": "false", "#text": "29.627601,-95.23823"}, "description": "ALMEDA GENOA RD | HFD | 11:35:04", "pubDate": "Mon, 21 Aug 2023 11:35:04 CDT", "active_status": "no"}, {"title": "Woods on Fire", "link": "http://maps.google.com/maps?q=29.734444,-95.302748", "guid": {"@isPermaLink": "false", "#text": "29.734444,-95.302748"}, "description": "CAPITOL ST | HFD | 12:00:06", "pubDate": "Mon, 21 Aug 2023 12:00:06 CDT", "active_status": "no"}, {"title": "Fire Event", "link": "http://maps.google.com/maps?q=29.764703,-95.391181", "guid": {"@isPermaLink": "false", "#text": "29.764703,-95.391181"}, "description": "MEMORIAL CT | HFD | 12:00:06", "pubDate": "Mon, 21 Aug 2023 12:00:06 CDT", "active_status": "no"}, {"title": "Car Fire", "link": "http://maps.google.com/maps?q=29.716741,-95.528307", "guid": {"@isPermaLink": "false", "#text": "29.716741,-95.528307"}, "description": "ALLDAY DR | HFD | 12:00:06", "pubDate": "Mon, 21 Aug 2023 12:00:06 CDT", "active_status": "no"}, {"title": "Fire Event", "link": "http://maps.google.com/maps?q=29.811513,-95.48692", "guid": {"@isPermaLink": "false", "#text": "29.811513,-95.48692"}, "description": "TURQUOISE LN | HFD | 12:40:04", "pubDate": "Mon, 21 Aug 2023 12:40:04 CDT", "active_status": "no"}, {"title": "Tree on Fire", "link": "http://maps.google.com/maps?q=29.863299,-95.47341", "guid": {"@isPermaLink": "false", "#text": "29.863299,-95.47341"}, "description": "ANTOINE DR  | HFD | 13:20:07", "pubDate": "Mon, 21 Aug 2023 13:20:07 CDT", "active_status": "no"}, {"title": "Grass Fire", "link": "http://maps.google.com/maps?q=29.856605,-95.327313", "guid": {"@isPermaLink": "false", "#text": "29.856605,-95.327313"}, "description": "AMALIE ST | HFD | 14:00:06", "pubDate": "Mon, 21 Aug 2023 14:00:06 CDT", "active_status": "no"}, {"title": "Car Fire", "link": "http://maps.google.com/maps?q=29.700327,-95.287459", "guid": {"@isPermaLink": "false", "#text": "29.700327,-95.287459"}, "description": "OFFICE CITY DR | HFD | 14:00:06", "pubDate": "Mon, 21 Aug 2023 14:00:06 CDT", "active_status": "no"}, {"title": "Fire Event", "link": "http://maps.google.com/maps?q=29.833976,-95.421798", "guid": {"@isPermaLink": "false", "#text": "29.833976,-95.421798"}, "description": "CHESHIRE LN | HFD | 14:10:04", "pubDate": "Mon, 21 Aug 2023 14:10:04 CDT", "active_status": "no"}, {"title": "Fire Event", "link": "http://maps.google.com/maps?q=30.051534,-95.245629", "guid": {"@isPermaLink": "false", "#text": "30.051534,-95.245629"}, "description": "KINGWOOD DR  | HFD | 14:15:04", "pubDate": "Mon, 21 Aug 2023 14:15:04 CDT", "active_status": "no"}, {"title": "Fire Event", "link": "http://maps.google.com/maps?q=29.829544,-95.492549", "guid": {"@isPermaLink": "false", "#text": "29.829544,-95.492549"}, "description": "FELDSPAR ST | HFD | 14:40:04", "pubDate": "Mon, 21 Aug 2023 14:40:04 CDT", "active_status": "no"}, {"title": "Fire Event", "link": "http://maps.google.com/maps?q=29.64104,-95.399289", "guid": {"@isPermaLink": "false", "#text": "29.64104,-95.399289"}, "description": "KIRBY LANDING DR | HFD | 14:55:04", "pubDate": "Mon, 21 Aug 2023 14:55:04 CDT", "active_status": "no"}, {"title": "Trash Fire", "link": "http://maps.google.com/maps?q=29.743535,-95.366634", "guid": {"@isPermaLink": "false", "#text": "29.743535,-95.366634"}, "description": "JACKSON ST | HFD | 14:55:04", "pubDate": "Mon, 21 Aug 2023 14:55:04 CDT", "active_status": "no"}, {"title": "Trash Fire", "link": "http://maps.google.com/maps?q=29.730958,-95.456219", "guid": {"@isPermaLink": "false", "#text": "29.730958,-95.456219"}, "description": "MERWIN ST | HFD | 15:00:03", "pubDate": "Mon, 21 Aug 2023 15:00:03 CDT", "active_status": "no"}, {"title": "Fire Event", "link": "http://maps.google.com/maps?q=29.757061,-95.378077", "guid": {"@isPermaLink": "false", "#text": "29.757061,-95.378077"}, "description": "SAULNIER ST | HFD | 15:00:03", "pubDate": "Mon, 21 Aug 2023 15:00:03 CDT", "active_status": "no"}, {"title": "Grass Fire", "link": "http://maps.google.com/maps?q=29.731782,-95.456324", "guid": {"@isPermaLink": "false", "#text": "29.731782,-95.456324"}, "description": "INGERSOLL ST | HFD | 15:00:03", "pubDate": "Mon, 21 Aug 2023 15:00:03 CDT", "active_status": "no"}, {"title": "Fire Event", "link": "http://maps.google.com/maps?q=29.580069,-95.514526", "guid": {"@isPermaLink": "false", "#text": "29.580069,-95.514526"}, "description": "MCHARD RD  | HFD | 15:00:03", "pubDate": "Mon, 21 Aug 2023 15:00:03 CDT", "active_status": "no"}, {"title": "Fire Event", "link": "http://maps.google.com/maps?q=29.659776,-95.348671", "guid": {"@isPermaLink": "false", "#text": "29.659776,-95.348671"}, "description": "MALLOW ST | HFD | 15:30:04", "pubDate": "Mon, 21 Aug 2023 15:30:04 CDT", "active_status": "no"}, {"title": "Fire Event", "link": "http://maps.google.com/maps?q=29.75278,-95.459576", "guid": {"@isPermaLink": "false", "#text": "29.75278,-95.459576"}, "description": "POST OAK BLVD | HFD | 15:45:04", "pubDate": "Mon, 21 Aug 2023 15:45:04 CDT", "active_status": "no"}, {"title": "Tree on Fire", "link": "http://maps.google.com/maps?q=29.77545,-95.291481", "guid": {"@isPermaLink": "false", "#text": "29.77545,-95.291481"}, "description": "N WAYSIDE DR | HFD | 16:20:04", "pubDate": "Mon, 21 Aug 2023 16:20:04 CDT", "active_status": "no"}, {"title": "Apartment Fire", "link": "http://maps.google.com/maps?q=29.785345,-95.397595", "guid": {"@isPermaLink": "false", "#text": "29.785345,-95.397595"}, "description": "HEIGHTS BLVD | HFD | 16:40:04", "pubDate": "Mon, 21 Aug 2023 16:40:04 CDT", "active_status": "no"}, {"title": "Fire Event", "link": "http://maps.google.com/maps?q=29.703867,-95.5757", "guid": {"@isPermaLink": "false", "#text": "29.703867,-95.5757"}, "description": "BELLAIRE BLVD | HFD | 16:40:04", "pubDate": "Mon, 21 Aug 2023 16:40:04 CDT", "active_status": "no"}, {"title": "Trash Fire", "link": "http://maps.google.com/maps?q=29.725554,-95.361208", "guid": {"@isPermaLink": "false", "#text": "29.725554,-95.361208"}, "description": "TRUXILLO ST | HFD | 17:15:04", "pubDate": "Mon, 21 Aug 2023 17:15:04 CDT", "active_status": "no"}, {"title": "Fire Event", "link": "http://maps.google.com/maps?q=29.725138,-95.369506", "guid": {"@isPermaLink": "false", "#text": "29.725138,-95.369506"}, "description": "ROSEWOOD ST | HFD | 17:25:04", "pubDate": "Mon, 21 Aug 2023 17:25:04 CDT", "active_status": "no"}, {"title": "Trash Fire", "link": "http://maps.google.com/maps?q=29.738091,-95.381133", "guid": {"@isPermaLink": "false", "#text": "29.738091,-95.381133"}, "description": "SOUTHWEST FWY IB  | HFD | 17:25:04", "pubDate": "Mon, 21 Aug 2023 17:25:04 CDT", "active_status": "no"}, {"title": "Grass Fire", "link": "http://maps.google.com/maps?q=29.732429,-95.384446", "guid": {"@isPermaLink": "false", "#text": "29.732429,-95.384446"}, "description": "MAIN-SUS59OB MAIN ST | HFD | 17:25:04", "pubDate": "Mon, 21 Aug 2023 17:25:04 CDT", "active_status": "no"}, {"title": "Grass Fire", "link": "http://maps.google.com/maps?q=29.735328,-95.384593", "guid": {"@isPermaLink": "false", "#text": "29.735328,-95.384593"}, "description": "SPUR527IB-COLQUITT SPUR 527 FWY | HFD | 17:45:04", "pubDate": "Mon, 21 Aug 2023 17:45:04 CDT", "active_status": "no"}, {"title": "Fire Event", "link": "http://maps.google.com/maps?q=29.93947,-95.396397", "guid": {"@isPermaLink": "false", "#text": "29.93947,-95.396397"}, "description": "N SAM HOUSTON PKWY E | HFD | 18:00:04", "pubDate": "Mon, 21 Aug 2023 18:00:04 CDT", "active_status": "no"}, {"title": "Fire Event", "link": "http://maps.google.com/maps?q=29.836227,-95.286333", "guid": {"@isPermaLink": "false", "#text": "29.836227,-95.286333"}, "description": "CAROLWOOD DR | HFD | 18:15:04", "pubDate": "Mon, 21 Aug 2023 18:15:04 CDT", "active_status": "no"}, {"title": "Apartment Fire", "link": "http://maps.google.com/maps?q=29.726094,-95.52559", "guid": {"@isPermaLink": "false", "#text": "29.726094,-95.52559"}, "description": "PAGEWOOD LN | HFD | 18:25:04", "pubDate": "Mon, 21 Aug 2023 18:25:04 CDT", "active_status": "no"}, {"title": "Car Fire", "link": "http://maps.google.com/maps?q=29.784445,-95.586887", "guid": {"@isPermaLink": "false", "#text": "29.784445,-95.586887"}, "description": "EXIT 755 W IH 10 FWY IB | HFD | 18:30:04", "pubDate": "Mon, 21 Aug 2023 18:30:04 CDT", "active_status": "no"}, {"title": "Fire Event", "link": "http://maps.google.com/maps?q=29.943764,-95.397986", "guid": {"@isPermaLink": "false", "#text": "29.943764,-95.397986"}, "description": "BENMAR DR | HFD | 18:30:04", "pubDate": "Mon, 21 Aug 2023 18:30:04 CDT", "active_status": "no"}, {"title": "Fire Event", "link": "http://maps.google.com/maps?q=29.577237,-95.119872", "guid": {"@isPermaLink": "false", "#text": "29.577237,-95.119872"}, "description": "HILLSIDE FALLS TRL | HFD | 19:00:04", "pubDate": "Mon, 21 Aug 2023 19:00:04 CDT", "active_status": "no"}, {"title": "Fire Event", "link": "http://maps.google.com/maps?q=29.752769,-95.378137", "guid": {"@isPermaLink": "false", "#text": "29.752769,-95.378137"}, "description": "GRAY ST | HFD | 19:15:04", "pubDate": "Mon, 21 Aug 2023 19:15:04 CDT", "active_status": "no"}, {"title": "Apartment Fire", "link": "http://maps.google.com/maps?q=29.690535,-95.548128", "guid": {"@isPermaLink": "false", "#text": "29.690535,-95.548128"}, "description": "BEECHNUT ST | HFD | 19:25:04", "pubDate": "Mon, 21 Aug 2023 19:25:04 CDT", "active_status": "no"}, {"title": "Apartment Fire", "link": "http://maps.google.com/maps?q=29.741954,-95.464222", "guid": {"@isPermaLink": "false", "#text": "29.741954,-95.464222"}, "description": "MCCUE RD | HFD | 19:40:04", "pubDate": "Mon, 21 Aug 2023 19:40:04 CDT", "active_status": "no"}, {"title": "Grass Fire", "link": "http://maps.google.com/maps?q=29.797365,-95.265654", "guid": {"@isPermaLink": "false", "#text": "29.797365,-95.265654"}, "description": "MANITOU DR  | HFD | 19:45:04", "pubDate": "Mon, 21 Aug 2023 19:45:04 CDT", "active_status": "no"}, {"title": "Trash Fire", "link": "http://maps.google.com/maps?q=29.865428,-95.370969", "guid": {"@isPermaLink": "false", "#text": "29.865428,-95.370969"}, "description": "GRENFELL LN | HFD | 19:50:04", "pubDate": "Mon, 21 Aug 2023 19:50:04 CDT", "active_status": "no"}, {"title": "Vehicle on Fire", "link": "http://maps.google.com/maps?q=29.81372,-95.459222", "guid": {"@isPermaLink": "false", "#text": "29.81372,-95.459222"}, "description": "MANGUM RD | HFD | 19:50:04", "pubDate": "Mon, 21 Aug 2023 19:50:04 CDT", "active_status": "no"}, {"title": "Fire Event", "link": "http://maps.google.com/maps?q=29.669065,-95.351502", "guid": {"@isPermaLink": "false", "#text": "29.669065,-95.351502"}, "description": "SUNFLOWER ST | HFD | 20:00:04", "pubDate": "Mon, 21 Aug 2023 20:00:04 CDT", "active_status": "no"}, {"title": "Fire Event", "link": "http://maps.google.com/maps?q=29.857017,-95.278097", "guid": {"@isPermaLink": "false", "#text": "29.857017,-95.278097"}, "description": "CADDO RD  | HFD | 20:35:04", "pubDate": "Mon, 21 Aug 2023 20:35:04 CDT", "active_status": "no"}, {"title": "Fire Event", "link": "http://maps.google.com/maps?q=29.73862,-95.404786", "guid": {"@isPermaLink": "false", "#text": "29.73862,-95.404786"}, "description": "W ALABAMA ST | HFD | 20:40:04", "pubDate": "Mon, 21 Aug 2023 20:40:04 CDT", "active_status": "no"}, {"title": "Fire Event", "link": "http://maps.google.com/maps?q=29.762194,-95.360585", "guid": {"@isPermaLink": "false", "#text": "29.762194,-95.360585"}, "description": "CONGRESS ST | HFD | 20:55:04", "pubDate": "Mon, 21 Aug 2023 20:55:04 CDT", "active_status": "no"}, {"title": "Fire Event", "link": "http://maps.google.com/maps?q=29.783658,-95.467978", "guid": {"@isPermaLink": "false", "#text": "29.783658,-95.467978"}, "description": "KATY FWY IB  | HFD | 21:20:05", "pubDate": "Mon, 21 Aug 2023 21:20:05 CDT", "active_status": "no"}, {"title": "Fire Event", "link": "http://maps.google.com/maps?q=29.778084,-95.391762", "guid": {"@isPermaLink": "false", "#text": "29.778084,-95.391762"}, "description": "OXFORD ST | HFD | 21:20:05", "pubDate": "Mon, 21 Aug 2023 21:20:05 CDT", "active_status": "no"}, {"title": "Dumpster on Fire", "link": "http://maps.google.com/maps?q=29.833225,-95.485318", "guid": {"@isPermaLink": "false", "#text": "29.833225,-95.485318"}, "description": "W 43RD ST | HFD | 22:00:03", "pubDate": "Mon, 21 Aug 2023 22:00:03 CDT", "active_status": "no"}, {"title": "Fire Event", "link": "http://maps.google.com/maps?q=29.765907,-95.63731", "guid": {"@isPermaLink": "false", "#text": "29.765907,-95.63731"}, "description": "FOREST HOME DR | HFD | 22:15:04", "pubDate": "Mon, 21 Aug 2023 22:15:04 CDT", "active_status": "yes"}, {"title": "Fire Event", "link": "http://maps.google.com/maps?q=29.853226,-95.283415", "guid": {"@isPermaLink": "false", "#text": "29.853226,-95.283415"}, "description": "LOCKSLEY RD | HFD | 22:50:07", "pubDate": "Mon, 21 Aug 2023 22:50:07 CDT", "active_status": "no"}, {"title": "Fire Event", "link": "http://maps.google.com/maps?q=29.660154,-95.312276", "guid": {"@isPermaLink": "false", "#text": "29.660154,-95.312276"}, "description": "REED RD | HFD | 22:55:04", "pubDate": "Mon, 21 Aug 2023 22:55:04 CDT", "active_status": "no"}, {"title": "Car Fire", "link": "http://maps.google.com/maps?q=29.763561,-95.364784", "guid": {"@isPermaLink": "false", "#text": "29.763561,-95.364784"}, "description": "SMITH ST  | HFD | 23:20:04", "pubDate": "Mon, 21 Aug 2023 23:20:04 CDT", "active_status": "no"}]}}}