{"rss": {"channel": {"item": [{"title": "02 - Dumpster Fire", "link": "http://maps.google.com/maps?q=32.763006,-96.750350", "guid": {"@isPermaLink": "false", "#text": "32.763006,-96.750350"}, "description": "3309 Carpenter Ave | DFD | 00:05:04", "pubDate": "Thu, 18 Sep 2025 00:05:04 CDT", "active_status": "no"}, {"title": "08 - Vehicle Fire", "link": "http://maps.google.com/maps?q=32.918251,-96.766165", "guid": {"@isPermaLink": "false", "#text": "32.918251,-96.766165"}, "description": "12340-12498 N Central Expy Nb | DFD | 01:10:05", "pubDate": "Thu, 18 Sep 2025 01:10:05 CDT", "active_status": "no"}, {"title": "42 - Automatic Fire Alarm", "link": "http://maps.google.com/maps?q=32.881312,-96.887508", "guid": {"@isPermaLink": "false", "#text": "32.881312,-96.887508"}, "description": "2671 Walnut Hill Ln | DFD | 01:25:04", "pubDate": "Thu, 18 Sep 2025 01:25:04 CDT", "active_status": "no"}, {"title": "01 - Grass Fire", "link": "http://maps.google.com/maps?q=32.714355,-96.682764", "guid": {"@isPermaLink": "false", "#text": "32.714355,-96.682764"}, "description": "140 S Buckner Blvd | DFD | 01:25:05", "pubDate": "Thu, 18 Sep 2025 01:25:05 CDT", "active_status": "no"}, {"title": "69 - STRUCTURE FIRE", "link": "http://maps.google.com/maps?q=32.783341,-96.685669", "guid": {"@isPermaLink": "false", "#text": "32.783341,-96.685669"}, "description": "8003 Rothington Rd | DFD | 02:55:04", "pubDate": "Thu, 18 Sep 2025 02:55:04 CDT", "active_status": "no"}, {"title": "42 - Automatic Fire Alarm", "link": "http://maps.google.com/maps?q=32.806886,-96.791672", "guid": {"@isPermaLink": "false", "#text": "32.806886,-96.791672"}, "description": "2750 N Haskell Ave | DFD | 04:35:04", "pubDate": "Thu, 18 Sep 2025 04:35:04 CDT", "active_status": "no"}, {"title": "02 - Dumpster Fire", "link": "http://maps.google.com/maps?q=32.881177,-96.890392", "guid": {"@isPermaLink": "false", "#text": "32.881177,-96.890392"}, "description": "Walnut Hill Ln / Shady Trl | DFD | 04:45:04", "pubDate": "Thu, 18 Sep 2025 04:45:04 CDT", "active_status": "no"}, {"title": "69 - STRUCTURE FIRE", "link": "http://maps.google.com/maps?q=32.953847,-96.807704", "guid": {"@isPermaLink": "false", "#text": "32.953847,-96.807704"}, "description": "5850 BELT LINE RD | DFD | 05:50:05", "pubDate": "Thu, 18 Sep 2025 05:50:05 CDT", "active_status": "no"}, {"title": "01 - Grass Fire", "link": "http://maps.google.com/maps?q=32.862555,-96.893938", "guid": {"@isPermaLink": "false", "#text": "32.862555,-96.893938"}, "description": "N Stemmons Fwy Sb / W Northwest Hwy | DFD | 07:35:04", "pubDate": "Thu, 18 Sep 2025 07:35:04 CDT", "active_status": "no"}, {"title": "69W - STRUCTURE FIRE WORKING", "link": "http://maps.google.com/maps?q=32.711703,-96.763968", "guid": {"@isPermaLink": "false", "#text": "32.711703,-96.763968"}, "description": "3335 Linfield Rd | DFD | 07:55:06", "pubDate": "Thu, 18 Sep 2025 07:55:06 CDT", "active_status": "no"}, {"title": "08 - Vehicle Fire", "link": "http://maps.google.com/maps?q=32.792578,-96.764096", "guid": {"@isPermaLink": "false", "#text": "32.792578,-96.764096"}, "description": "4724 East Side Ave | DFD | 08:00:06", "pubDate": "Thu, 18 Sep 2025 08:00:06 CDT", "active_status": "no"}, {"title": "69 - STRUCTURE FIRE", "link": "http://maps.google.com/maps?q=32.954282,-96.821040", "guid": {"@isPermaLink": "false", "#text": "32.954282,-96.821040"}, "description": "5151 Belt Line Rd | DFD | 14:10:05", "pubDate": "Thu, 18 Sep 2025 14:10:05 CDT", "active_status": "no"}, {"title": "10F - Fire Reported Out", "link": "http://maps.google.com/maps?q=32.714551,-96.714263", "guid": {"@isPermaLink": "false", "#text": "32.714551,-96.714263"}, "description": "221 Stoneport Dr | DFD | 15:40:08", "pubDate": "Thu, 18 Sep 2025 15:40:08 CDT", "active_status": "no"}, {"title": "69W - STRUCTURE FIRE WORKING", "link": "http://maps.google.com/maps?q=32.722211,-96.824997", "guid": {"@isPermaLink": "false", "#text": "32.722211,-96.824997"}, "description": "218 W Woodin Blvd | DFD | 16:10:05", "pubDate": "Thu, 18 Sep 2025 16:10:05 CDT", "active_status": "no"}, {"title": "69W - STRUCTURE FIRE WORKING", "link": "http://maps.google.com/maps?q=32.722485,-96.824785", "guid": {"@isPermaLink": "false", "#text": "32.722485,-96.824785"}, "description": "207 W WOODIN BLVD | DFD | 17:30:05", "pubDate": "Thu, 18 Sep 2025 17:30:05 CDT", "active_status": "no"}, {"title": "01 - Grass Fire", "link": "http://maps.google.com/maps?q=32.835604,-96.875448", "guid": {"@isPermaLink": "false", "#text": "32.835604,-96.875448"}, "description": "N Stemmons Serv Sb / Regal Row | DFD | 18:10:05", "pubDate": "Thu, 18 Sep 2025 18:10:05 CDT", "active_status": "no"}, {"title": "01 - Grass Fire", "link": "http://maps.google.com/maps?q=32.837864,-96.874594", "guid": {"@isPermaLink": "false", "#text": "32.837864,-96.874594"}, "description": "9090 N Stemmons Serv Nb | DFD | 18:45:04", "pubDate": "Thu, 18 Sep 2025 18:45:04 CDT", "active_status": "no"}, {"title": "69 - STRUCTURE FIRE", "link": "http://maps.google.com/maps?q=32.795561,-96.721905", "guid": {"@isPermaLink": "false", "#text": "32.795561,-96.721905"}, "description": "7229 FERGUSON RD | DFD | 20:00:05", "pubDate": "Thu, 18 Sep 2025 20:00:05 CDT", "active_status": "no"}, {"title": "04 - Trash Fire", "link": "http://maps.google.com/maps?q=32.864336,-96.771518", "guid": {"@isPermaLink": "false", "#text": "32.864336,-96.771518"}, "description": "0 E Northwest Ramp Eb | DFD | 21:10:03", "pubDate": "Thu, 18 Sep 2025 21:10:03 CDT", "active_status": "no"}, {"title": "08 - Vehicle Fire", "link": "http://maps.google.com/maps?q=32.790787,-96.769923", "guid": {"@isPermaLink": "false", "#text": "32.790787,-96.769923"}, "description": "N PEAK ST / ELM ST | DFD | 21:55:05", "pubDate": "Thu, 18 Sep 2025 21:55:05 CDT", "active_status": "no"}, {"title": "01 - Grass Fire", "link": "http://maps.google.com/maps?q=32.754087,-96.654891", "guid": {"@isPermaLink": "false", "#text": "32.754087,-96.654891"}, "description": "2516 Mossglen Dr | DFD | 22:25:05", "pubDate": "Thu, 18 Sep 2025 22:25:05 CDT", "active_status": "yes"}]}}}