{"rss": {"channel": {"item": [{"title": "OUTSIDE FIRE - B", "link": "http://maps.google.com/maps?q=33.700466,-116.189418", "guid": {"@isPermaLink": "false", "#text": "33.700466,-116.189418"}, "description": "84498 CABAZON AV / 84500 DILLON RD  | RFD | 00:00:43", "pubDate": "Tue, 02 May 2023 00:00:43 CDT", "active_status": "no"}, {"title": "FIRE ALARM UNKNOWN - B", "link": "http://maps.google.com/maps?q=33.681506,-116.288156", "guid": {"@isPermaLink": "false", "#text": "33.681506,-116.288156"}, "description": "50460 SPYGLASS HILL DR  | RFD | 00:00:43", "pubDate": "Tue, 02 May 2023 00:00:43 CDT", "active_status": "no"}, {"title": "OUTSIDE FIRE - D", "link": "http://maps.google.com/maps?q=33.698633,-116.218541", "guid": {"@isPermaLink": "false", "#text": "33.698633,-116.218541"}, "description": "48160 GARBO DR  | RFD | 00:00:43", "pubDate": "Tue, 02 May 2023 00:00:43 CDT", "active_status": "no"}, {"title": "VEGETATION FIRE - D", "link": "http://maps.google.com/maps?q=33.554701,-116.112720", "guid": {"@isPermaLink": "false", "#text": "33.554701,-116.112720"}, "description": "68000 PIERCE ST / 89000 AVE 68  | RFD | 00:00:43", "pubDate": "Tue, 02 May 2023 00:00:43 CDT", "active_status": "no"}, {"title": "RESIDENTIAL STR FIRE - D", "link": "http://maps.google.com/maps?q=33.923068,-116.440490", "guid": {"@isPermaLink": "false", "#text": "33.923068,-116.440490"}, "description": "17300 CORKILL RD  | RFD | 02:15:32", "pubDate": "Tue, 02 May 2023 02:15:32 CDT", "active_status": "no"}, {"title": "FIRE/ FALSE ALARM", "link": "http://maps.google.com/maps?q=33.592518,-116.751825", "guid": {"@isPermaLink": "false", "#text": "33.592518,-116.751825"}, "description": "36401 TRIPP FLATS RD  | RFD | 02:20:34", "pubDate": "Tue, 02 May 2023 02:20:34 CDT", "active_status": "no"}, {"title": "RESIDENTIAL STR FIRE - E", "link": "http://maps.google.com/maps?q=33.957441,-116.997047", "guid": {"@isPermaLink": "false", "#text": "33.957441,-116.997047"}, "description": "1707 LAS COLINAS RD  | RFD | 04:15:17", "pubDate": "Tue, 02 May 2023 04:15:17 CDT", "active_status": "no"}, {"title": "FIRE/ FALSE ALARM", "link": "http://maps.google.com/maps?q=33.697796,-116.290064", "guid": {"@isPermaLink": "false", "#text": "33.697796,-116.290064"}, "description": "48285 PASO TIEMPO LN  | RFD | 04:35:16", "pubDate": "Tue, 02 May 2023 04:35:16 CDT", "active_status": "no"}, {"title": "VEGETATION FIRE - C", "link": "http://maps.google.com/maps?q=33.825407,-114.534995", "guid": {"@isPermaLink": "false", "#text": "33.825407,-114.534995"}, "description": "30100 HY 95 /   RIVER ACCESS RD  | RFD | 06:05:13", "pubDate": "Tue, 02 May 2023 06:05:13 CDT", "active_status": "no"}, {"title": "FIRE/ FALSE ALARM", "link": "http://maps.google.com/maps?q=33.794051,-116.965025", "guid": {"@isPermaLink": "false", "#text": "33.794051,-116.965025"}, "description": "SAN JACINTO HIGH SCH @ 500 IDYLLWILD DR  | RFD | 07:00:17", "pubDate": "Tue, 02 May 2023 07:00:17 CDT", "active_status": "no"}, {"title": "TRAFFIC COLISN W/ FIRE- D", "link": "http://maps.google.com/maps?q=33.961435,-116.545022", "guid": {"@isPermaLink": "false", "#text": "33.961435,-116.545022"}, "description": "12000 N INDIAN CANYON DR / 64000 PIERSON BL  | RFD | 08:50:20", "pubDate": "Tue, 02 May 2023 08:50:20 CDT", "active_status": "no"}, {"title": "RESIDENTIAL STR FIRE - E", "link": "http://maps.google.com/maps?q=33.841268,-117.325486", "guid": {"@isPermaLink": "false", "#text": "33.841268,-117.325486"}, "description": "19323 COPPER RIDGE ST  | RFD | 09:15:17", "pubDate": "Tue, 02 May 2023 09:15:17 CDT", "active_status": "no"}, {"title": "FIRE/ FALSE ALARM", "link": "http://maps.google.com/maps?q=33.719773,-116.390378", "guid": {"@isPermaLink": "false", "#text": "33.719773,-116.390378"}, "description": "73052 EL PASEO  | RFD | 09:55:14", "pubDate": "Tue, 02 May 2023 09:55:14 CDT", "active_status": "no"}, {"title": "COMMERCIAL STR FIRE - D", "link": "http://maps.google.com/maps?q=33.954830,-116.998347", "guid": {"@isPermaLink": "false", "#text": "33.954830,-116.998347"}, "description": "SOLERA SENIOR COMMUNITY @ 1615 FAIRWAY DR  | RFD | 10:45:13", "pubDate": "Tue, 02 May 2023 10:45:13 CDT", "active_status": "no"}, {"title": "VEHICLE FIRE - B", "link": "http://maps.google.com/maps?q=33.926755,-116.940465", "guid": {"@isPermaLink": "false", "#text": "33.926755,-116.940465"}, "description": "I 10 W WO   HIGHLAND SPRINGS AV OFRP  | RFD | 11:05:15", "pubDate": "Tue, 02 May 2023 11:05:15 CDT", "active_status": "no"}, {"title": "RESIDENTIAL STR FIRE - D", "link": "http://maps.google.com/maps?q=34.013773,-117.472915", "guid": {"@isPermaLink": "false", "#text": "34.013773,-117.472915"}, "description": "4071 FIRCREST LN  | RFD | 11:20:14", "pubDate": "Tue, 02 May 2023 11:20:14 CDT", "active_status": "no"}, {"title": "FIRE/ FALSE ALARM", "link": "http://maps.google.com/maps?q=33.777880,-116.425007", "guid": {"@isPermaLink": "false", "#text": "33.777880,-116.425007"}, "description": "70901 FAIRWAY DR  | RFD | 12:15:12", "pubDate": "Tue, 02 May 2023 12:15:12 CDT", "active_status": "no"}, {"title": "VEGETATION FIRE - C", "link": "http://maps.google.com/maps?q=33.939453,-116.486200", "guid": {"@isPermaLink": "false", "#text": "33.939453,-116.486200"}, "description": "BUBBLING WELLS ELEMENTARY SCH @ 67501 CAMINO CAMPANERO  | RFD | 12:40:18", "pubDate": "Tue, 02 May 2023 12:40:18 CDT", "active_status": "no"}, {"title": "VEGETATION FIRE", "link": "http://maps.google.com/maps?q=33.883150,-117.352467", "guid": {"@isPermaLink": "false", "#text": "33.883150,-117.352467"}, "description": "=L(33.883150 | RFD | 13:50:14", "pubDate": "Tue, 02 May 2023 13:50:14 CDT", "active_status": "no"}, {"title": "RESIDENTIAL STR FIRE - E", "link": "http://maps.google.com/maps?q=33.781389,-117.504325", "guid": {"@isPermaLink": "false", "#text": "33.781389,-117.504325"}, "description": "8899 DAHLIA DR  | RFD | 14:10:16", "pubDate": "Tue, 02 May 2023 14:10:16 CDT", "active_status": "no"}, {"title": "RESIDENTIAL STR FIRE - D", "link": "http://maps.google.com/maps?q=33.946979,-117.230860", "guid": {"@isPermaLink": "false", "#text": "33.946979,-117.230860"}, "description": "11977 HUBBARD ST  | RFD | 14:55:16", "pubDate": "Tue, 02 May 2023 14:55:16 CDT", "active_status": "no"}, {"title": "FIRE/ FALSE ALARM", "link": "http://maps.google.com/maps?q=34.001040,-117.414937", "guid": {"@isPermaLink": "false", "#text": "34.001040,-117.414937"}, "description": "5875 MISSION BL  | RFD | 15:15:13", "pubDate": "Tue, 02 May 2023 15:15:13 CDT", "active_status": "no"}, {"title": "FIRE/ FALSE ALARM", "link": "http://maps.google.com/maps?q=33.491487,-117.086270", "guid": {"@isPermaLink": "false", "#text": "33.491487,-117.086270"}, "description": "43799 SUNNY MEADOWS DR  | RFD | 16:30:29", "pubDate": "Tue, 02 May 2023 16:30:29 CDT", "active_status": "no"}, {"title": "VEGETATION FIRE - D", "link": "http://maps.google.com/maps?q=34.006174,-117.502665", "guid": {"@isPermaLink": "false", "#text": "34.006174,-117.502665"}, "description": "9998 BELLEGRAVE AV / 9801 VAN BUREN BL  | RFD | 16:35:23", "pubDate": "Tue, 02 May 2023 16:35:23 CDT", "active_status": "no"}, {"title": "FIRE/ FALSE ALARM", "link": "http://maps.google.com/maps?q=33.724409,-116.391252", "guid": {"@isPermaLink": "false", "#text": "33.724409,-116.391252"}, "description": "ATRIA HACIENDA @ 44600 MONTEREY AV  | RFD | 16:35:23", "pubDate": "Tue, 02 May 2023 16:35:23 CDT", "active_status": "no"}, {"title": "RESIDENTIAL STR FIRE - E", "link": "http://maps.google.com/maps?q=33.951172,-117.525672", "guid": {"@isPermaLink": "false", "#text": "33.951172,-117.525672"}, "description": "186 8TH ST  | RFD | 16:55:20", "pubDate": "Tue, 02 May 2023 16:55:20 CDT", "active_status": "no"}, {"title": "OUTSIDE FIRE - B", "link": "http://maps.google.com/maps?q=33.477376,-117.139752", "guid": {"@isPermaLink": "false", "#text": "33.477376,-117.139752"}, "description": "I 15 S SO   TEMECULA PY ONRP  | RFD | 17:50:17", "pubDate": "Tue, 02 May 2023 17:50:17 CDT", "active_status": "no"}, {"title": "COMMERCIAL STR FIRE - E", "link": "http://maps.google.com/maps?q=33.925407,-116.891215", "guid": {"@isPermaLink": "false", "#text": "33.925407,-116.891215"}, "description": "1330 W RAMSEY ST  | RFD | 18:30:15", "pubDate": "Tue, 02 May 2023 18:30:15 CDT", "active_status": "no"}, {"title": "FIRE/ FALSE ALARM", "link": "http://maps.google.com/maps?q=33.768986,-116.250932", "guid": {"@isPermaLink": "false", "#text": "33.768986,-116.250932"}, "description": "38618 CAMINO AGUACERO  | RFD | 18:45:21", "pubDate": "Tue, 02 May 2023 18:45:21 CDT", "active_status": "no"}, {"title": "RESIDENTIAL STR FIRE - D", "link": "http://maps.google.com/maps?q=33.636314,-116.265205", "guid": {"@isPermaLink": "false", "#text": "33.636314,-116.265205"}, "description": "56780 JACK NICKLAUS  | RFD | 20:15:20", "pubDate": "Tue, 02 May 2023 20:15:20 CDT", "active_status": "no"}, {"title": "VEGETATION FIRE OBL - A", "link": "http://maps.google.com/maps?q=33.878021,-117.206730", "guid": {"@isPermaLink": "false", "#text": "33.878021,-117.206730"}, "description": "16656 FOX TROT LN  | RFD | 20:50:16", "pubDate": "Tue, 02 May 2023 20:50:16 CDT", "active_status": "no"}, {"title": "VEGETATION FIRE - D", "link": "http://maps.google.com/maps?q=33.748567,-116.696353", "guid": {"@isPermaLink": "false", "#text": "33.748567,-116.696353"}, "description": "53320 RISING GLEN RD / 25800 GRANITE PL  | RFD | 21:25:28", "pubDate": "Tue, 02 May 2023 21:25:28 CDT", "active_status": "no"}, {"title": "FIRE/ FALSE ALARM", "link": "http://maps.google.com/maps?q=33.742063,-116.362954", "guid": {"@isPermaLink": "false", "#text": "33.742063,-116.362954"}, "description": "74501 AVE 42  | RFD | 21:55:22", "pubDate": "Tue, 02 May 2023 21:55:22 CDT", "active_status": "no"}, {"title": "OUTSIDE FIRE - B", "link": "http://maps.google.com/maps?q=33.680012,-117.390574", "guid": {"@isPermaLink": "false", "#text": "33.680012,-117.390574"}, "description": "15124 KNOLLWOOD ST  | RFD | 22:45:35", "pubDate": "Tue, 02 May 2023 22:45:35 CDT", "active_status": "no"}, {"title": "VEGETATION FIRE - C", "link": "http://maps.google.com/maps?q=33.947231,-117.580068", "guid": {"@isPermaLink": "false", "#text": "33.947231,-117.580068"}, "description": "7777 COBBLE CREEK DR  | RFD | 22:55:35", "pubDate": "Tue, 02 May 2023 22:55:35 CDT", "active_status": "yes"}, {"title": "FIRE/ FALSE ALARM", "link": "http://maps.google.com/maps?q=33.737706,-116.249945", "guid": {"@isPermaLink": "false", "#text": "33.737706,-116.249945"}, "description": "81077 INDIO BL  | RFD | 23:05:53", "pubDate": "Tue, 02 May 2023 23:05:53 CDT", "active_status": "no"}]}}}