{"rss": {"channel": {"item": [{"title": "Apartment Fire", "link": "http://maps.google.com/maps?q=29.858824,-95.505938", "guid": {"@isPermaLink": "false", "#text": "29.858824,-95.505938"}, "description": "WILSHIRE PLACE DR | HFD | 00:00:06", "pubDate": "Sun, 28 May 2023 00:00:06 CDT", "active_status": "no"}, {"title": "Trash Fire", "link": "http://maps.google.com/maps?q=29.738064,-95.28765", "guid": {"@isPermaLink": "false", "#text": "29.738064,-95.28765"}, "description": "AVENUE J  | HFD | 00:00:06", "pubDate": "Sun, 28 May 2023 00:00:06 CDT", "active_status": "no"}, {"title": "Bus Fire", "link": "http://maps.google.com/maps?q=29.772906,-95.326413", "guid": {"@isPermaLink": "false", "#text": "29.772906,-95.326413"}, "description": "EIH10IB-WACO ST E IH 10 FWY IB | HFD | 00:00:06", "pubDate": "Sun, 28 May 2023 00:00:06 CDT", "active_status": "no"}, {"title": "Fire Event", "link": "http://maps.google.com/maps?q=29.811552,-95.376925", "guid": {"@isPermaLink": "false", "#text": "29.811552,-95.376925"}, "description": "SYLVESTER RD | HFD | 00:05:10", "pubDate": "Sun, 28 May 2023 00:05:10 CDT", "active_status": "no"}, {"title": "Apartment Fire", "link": "http://maps.google.com/maps?q=29.814102,-95.458005", "guid": {"@isPermaLink": "false", "#text": "29.814102,-95.458005"}, "description": "SHERWOOD LN | HFD | 00:05:10", "pubDate": "Sun, 28 May 2023 00:05:10 CDT", "active_status": "no"}, {"title": "Car Fire", "link": "http://maps.google.com/maps?q=29.693589,-95.374977", "guid": {"@isPermaLink": "false", "#text": "29.693589,-95.374977"}, "description": "ALICE ST | HFD | 00:40:07", "pubDate": "Sun, 28 May 2023 00:40:07 CDT", "active_status": "no"}, {"title": "House on Fire", "link": "http://maps.google.com/maps?q=29.672192,-95.322328", "guid": {"@isPermaLink": "false", "#text": "29.672192,-95.322328"}, "description": "DOULTON DR | HFD | 00:50:06", "pubDate": "Sun, 28 May 2023 00:50:06 CDT", "active_status": "no"}, {"title": "Fire Event", "link": "http://maps.google.com/maps?q=29.712576,-95.393683", "guid": {"@isPermaLink": "false", "#text": "29.712576,-95.393683"}, "description": "TAUB LP | HFD | 01:10:05", "pubDate": "Sun, 28 May 2023 01:10:05 CDT", "active_status": "no"}, {"title": "Apartment Fire", "link": "http://maps.google.com/maps?q=29.728268,-95.353234", "guid": {"@isPermaLink": "false", "#text": "29.728268,-95.353234"}, "description": "FRANCIS ST | HFD | 01:45:05", "pubDate": "Sun, 28 May 2023 01:45:05 CDT", "active_status": "no"}, {"title": "Apartment Fire", "link": "http://maps.google.com/maps?q=29.738102,-95.498345", "guid": {"@isPermaLink": "false", "#text": "29.738102,-95.498345"}, "description": "MARILEE LN | HFD | 02:00:06", "pubDate": "Sun, 28 May 2023 02:00:06 CDT", "active_status": "no"}, {"title": "Fire Event", "link": "http://maps.google.com/maps?q=29.781171,-95.456715", "guid": {"@isPermaLink": "false", "#text": "29.781171,-95.456715"}, "description": "N POST OAK RD | HFD | 02:40:04", "pubDate": "Sun, 28 May 2023 02:40:04 CDT", "active_status": "no"}, {"title": "Fire Event", "link": "http://maps.google.com/maps?q=29.610562,-95.434795", "guid": {"@isPermaLink": "false", "#text": "29.610562,-95.434795"}, "description": "BATHURST DR | HFD | 03:05:04", "pubDate": "Sun, 28 May 2023 03:05:04 CDT", "active_status": "no"}, {"title": "Fire Event", "link": "http://maps.google.com/maps?q=29.751195,-95.485899", "guid": {"@isPermaLink": "false", "#text": "29.751195,-95.485899"}, "description": "FOUNTAIN VIEW DR | HFD | 03:10:04", "pubDate": "Sun, 28 May 2023 03:10:04 CDT", "active_status": "no"}, {"title": "Apartment Fire", "link": "http://maps.google.com/maps?q=29.648299,-95.508339", "guid": {"@isPermaLink": "false", "#text": "29.648299,-95.508339"}, "description": "FONDREN RD | HFD | 03:25:04", "pubDate": "Sun, 28 May 2023 03:25:04 CDT", "active_status": "no"}, {"title": "Dumpster on Fire", "link": "http://maps.google.com/maps?q=29.899097,-95.41265", "guid": {"@isPermaLink": "false", "#text": "29.899097,-95.41265"}, "description": "NORTH FWY IB | HFD | 05:10:04", "pubDate": "Sun, 28 May 2023 05:10:04 CDT", "active_status": "no"}, {"title": "Fire Event", "link": "http://maps.google.com/maps?q=29.740714,-95.553435", "guid": {"@isPermaLink": "false", "#text": "29.740714,-95.553435"}, "description": "PIPING ROCK LN | HFD | 05:40:07", "pubDate": "Sun, 28 May 2023 05:40:07 CDT", "active_status": "no"}, {"title": "Building Fire", "link": "http://maps.google.com/maps?q=29.949116,-95.417708", "guid": {"@isPermaLink": "false", "#text": "29.949116,-95.417708"}, "description": "W GREENS RD | HFD | 05:40:07", "pubDate": "Sun, 28 May 2023 05:40:07 CDT", "active_status": "no"}, {"title": "Apartment Fire", "link": "http://maps.google.com/maps?q=29.730135,-95.468343", "guid": {"@isPermaLink": "false", "#text": "29.730135,-95.468343"}, "description": "BEVERLY HILL ST | HFD | 05:45:04", "pubDate": "Sun, 28 May 2023 05:45:04 CDT", "active_status": "no"}, {"title": "Apartment Fire", "link": "http://maps.google.com/maps?q=29.773299,-95.415447", "guid": {"@isPermaLink": "false", "#text": "29.773299,-95.415447"}, "description": "STUDER ST | HFD | 06:00:04", "pubDate": "Sun, 28 May 2023 06:00:04 CDT", "active_status": "no"}, {"title": "Trash Fire", "link": "http://maps.google.com/maps?q=29.777223,-95.38822", "guid": {"@isPermaLink": "false", "#text": "29.777223,-95.38822"}, "description": "STUDEMONT ST  | HFD | 06:40:07", "pubDate": "Sun, 28 May 2023 06:40:07 CDT", "active_status": "no"}, {"title": "Apartment Fire", "link": "http://maps.google.com/maps?q=29.697513,-95.331464", "guid": {"@isPermaLink": "false", "#text": "29.697513,-95.331464"}, "description": "ROYAL PALMS ST | HFD | 07:55:06", "pubDate": "Sun, 28 May 2023 07:55:06 CDT", "active_status": "no"}, {"title": "Fire Event", "link": "http://maps.google.com/maps?q=29.8878,-95.422605", "guid": {"@isPermaLink": "false", "#text": "29.8878,-95.422605"}, "description": "W GULF BANK RD | HFD | 08:15:04", "pubDate": "Sun, 28 May 2023 08:15:04 CDT", "active_status": "no"}, {"title": "Apartment Fire", "link": "http://maps.google.com/maps?q=29.688259,-95.505815", "guid": {"@isPermaLink": "false", "#text": "29.688259,-95.505815"}, "description": "BISSONNET ST | HFD | 08:20:04", "pubDate": "Sun, 28 May 2023 08:20:04 CDT", "active_status": "no"}, {"title": "Dumpster on Fire", "link": "http://maps.google.com/maps?q=29.89898,-95.412636", "guid": {"@isPermaLink": "false", "#text": "29.89898,-95.412636"}, "description": "NORTH FWY IB | HFD | 08:45:04", "pubDate": "Sun, 28 May 2023 08:45:04 CDT", "active_status": "no"}, {"title": "Fire Event", "link": "http://maps.google.com/maps?q=29.818279,-95.280291", "guid": {"@isPermaLink": "false", "#text": "29.818279,-95.280291"}, "description": "FILLTOP ST | HFD | 09:30:05", "pubDate": "Sun, 28 May 2023 09:30:05 CDT", "active_status": "no"}, {"title": "Trash Fire", "link": "http://maps.google.com/maps?q=29.698583,-95.583289", "guid": {"@isPermaLink": "false", "#text": "29.698583,-95.583289"}, "description": "SANDSTONE ST | HFD | 09:55:04", "pubDate": "Sun, 28 May 2023 09:55:04 CDT", "active_status": "no"}, {"title": "Fire Event", "link": "http://maps.google.com/maps?q=29.724308,-95.38708", "guid": {"@isPermaLink": "false", "#text": "29.724308,-95.38708"}, "description": "BINZ ST | HFD | 10:10:05", "pubDate": "Sun, 28 May 2023 10:10:05 CDT", "active_status": "no"}, {"title": "Fire Event", "link": "http://maps.google.com/maps?q=29.86553,-95.415991", "guid": {"@isPermaLink": "false", "#text": "29.86553,-95.415991"}, "description": "MILLVILLE DR | HFD | 10:15:05", "pubDate": "Sun, 28 May 2023 10:15:05 CDT", "active_status": "no"}, {"title": "Fire Event", "link": "http://maps.google.com/maps?q=29.860447,-95.422791", "guid": {"@isPermaLink": "false", "#text": "29.860447,-95.422791"}, "description": "KNOX ST | HFD | 10:50:05", "pubDate": "Sun, 28 May 2023 10:50:05 CDT", "active_status": "no"}, {"title": "Fire Event", "link": "http://maps.google.com/maps?q=29.756565,-95.408396", "guid": {"@isPermaLink": "false", "#text": "29.756565,-95.408396"}, "description": "S SHEPHERD DR | HFD | 10:50:05", "pubDate": "Sun, 28 May 2023 10:50:05 CDT", "active_status": "no"}, {"title": "Fire Event", "link": "http://maps.google.com/maps?q=29.860728,-95.440562", "guid": {"@isPermaLink": "false", "#text": "29.860728,-95.440562"}, "description": "COVINGTON DR | HFD | 12:00:06", "pubDate": "Sun, 28 May 2023 12:00:06 CDT", "active_status": "no"}, {"title": "Apartment Fire", "link": "http://maps.google.com/maps?q=29.70354,-95.537979", "guid": {"@isPermaLink": "false", "#text": "29.70354,-95.537979"}, "description": "S GESSNER RD | HFD | 12:10:05", "pubDate": "Sun, 28 May 2023 12:10:05 CDT", "active_status": "no"}, {"title": "Fire Event", "link": "http://maps.google.com/maps?q=29.873617,-95.366424", "guid": {"@isPermaLink": "false", "#text": "29.873617,-95.366424"}, "description": "W HARDY RD | HFD | 12:40:04", "pubDate": "Sun, 28 May 2023 12:40:04 CDT", "active_status": "no"}, {"title": "Fire Event", "link": "http://maps.google.com/maps?q=29.803867,-95.406194", "guid": {"@isPermaLink": "false", "#text": "29.803867,-95.406194"}, "description": "W 20TH ST | HFD | 12:45:20", "pubDate": "Sun, 28 May 2023 12:45:20 CDT", "active_status": "no"}, {"title": "House on Fire", "link": "http://maps.google.com/maps?q=29.67246,-95.305319", "guid": {"@isPermaLink": "false", "#text": "29.67246,-95.305319"}, "description": "GLEN ROCK DR | HFD | 13:25:06", "pubDate": "Sun, 28 May 2023 13:25:06 CDT", "active_status": "no"}, {"title": "Trash Fire", "link": "http://maps.google.com/maps?q=29.848394,-95.478537", "guid": {"@isPermaLink": "false", "#text": "29.848394,-95.478537"}, "description": "W SUNFOREST DR | HFD | 13:25:06", "pubDate": "Sun, 28 May 2023 13:25:06 CDT", "active_status": "no"}, {"title": "Trash Fire", "link": "http://maps.google.com/maps?q=29.686627,-95.561168", "guid": {"@isPermaLink": "false", "#text": "29.686627,-95.561168"}, "description": "SPICE LN | HFD | 13:55:05", "pubDate": "Sun, 28 May 2023 13:55:05 CDT", "active_status": "no"}, {"title": "Fire Event", "link": "http://maps.google.com/maps?q=29.702266,-95.277924", "guid": {"@isPermaLink": "false", "#text": "29.702266,-95.277924"}, "description": "SIH610OB-BROADWAY ST S IH 610 FWY E | HFD | 13:55:05", "pubDate": "Sun, 28 May 2023 13:55:05 CDT", "active_status": "no"}, {"title": "Fire Event", "link": "http://maps.google.com/maps?q=29.71646,-95.615153", "guid": {"@isPermaLink": "false", "#text": "29.71646,-95.615153"}, "description": "SYNOTT RD | HFD | 14:05:07", "pubDate": "Sun, 28 May 2023 14:05:07 CDT", "active_status": "no"}, {"title": "Fire Event", "link": "http://maps.google.com/maps?q=29.845083,-95.291379", "guid": {"@isPermaLink": "false", "#text": "29.845083,-95.291379"}, "description": "BELLINGHAM DR | HFD | 14:10:04", "pubDate": "Sun, 28 May 2023 14:10:04 CDT", "active_status": "no"}, {"title": "Trash Fire", "link": "http://maps.google.com/maps?q=29.736008,-95.28594", "guid": {"@isPermaLink": "false", "#text": "29.736008,-95.28594"}, "description": "AVENUE H | HFD | 14:20:06", "pubDate": "Sun, 28 May 2023 14:20:06 CDT", "active_status": "no"}, {"title": "Dumpster on Fire", "link": "http://maps.google.com/maps?q=29.691965,-95.297711", "guid": {"@isPermaLink": "false", "#text": "29.691965,-95.297711"}, "description": "SOUTHWAY DR | HFD | 14:55:05", "pubDate": "Sun, 28 May 2023 14:55:05 CDT", "active_status": "no"}, {"title": "Building Fire", "link": "http://maps.google.com/maps?q=29.73473,-95.501088", "guid": {"@isPermaLink": "false", "#text": "29.73473,-95.501088"}, "description": "HILLCROFT AVE | HFD | 14:55:05", "pubDate": "Sun, 28 May 2023 14:55:05 CDT", "active_status": "no"}, {"title": "Fire Event", "link": "http://maps.google.com/maps?q=29.740701,-95.463621", "guid": {"@isPermaLink": "false", "#text": "29.740701,-95.463621"}, "description": "WESTHEIMER RD | HFD | 15:00:05", "pubDate": "Sun, 28 May 2023 15:00:05 CDT", "active_status": "no"}, {"title": "Grass Fire", "link": "http://maps.google.com/maps?q=29.965593,-95.419554", "guid": {"@isPermaLink": "false", "#text": "29.965593,-95.419554"}, "description": "NORTH FWY IB  | HFD | 15:15:05", "pubDate": "Sun, 28 May 2023 15:15:05 CDT", "active_status": "no"}, {"title": "Apartment Fire", "link": "http://maps.google.com/maps?q=29.657675,-95.389471", "guid": {"@isPermaLink": "false", "#text": "29.657675,-95.389471"}, "description": "REED RD | HFD | 15:20:05", "pubDate": "Sun, 28 May 2023 15:20:05 CDT", "active_status": "no"}, {"title": "Car Fire", "link": "http://maps.google.com/maps?q=29.828622,-95.380669", "guid": {"@isPermaLink": "false", "#text": "29.828622,-95.380669"}, "description": "NORTH FWY OB  | HFD | 15:30:05", "pubDate": "Sun, 28 May 2023 15:30:05 CDT", "active_status": "no"}, {"title": "Fire Event", "link": "http://maps.google.com/maps?q=29.690796,-95.595932", "guid": {"@isPermaLink": "false", "#text": "29.690796,-95.595932"}, "description": "COOK RD | HFD | 16:00:04", "pubDate": "Sun, 28 May 2023 16:00:04 CDT", "active_status": "no"}, {"title": "Fire Event", "link": "http://maps.google.com/maps?q=29.83539,-95.331367", "guid": {"@isPermaLink": "false", "#text": "29.83539,-95.331367"}, "description": "DARDEN ST | HFD | 16:00:04", "pubDate": "Sun, 28 May 2023 16:00:04 CDT", "active_status": "no"}, {"title": "Grass Fire", "link": "http://maps.google.com/maps?q=29.900334,-95.412664", "guid": {"@isPermaLink": "false", "#text": "29.900334,-95.412664"}, "description": "NORTH FWY IB  | HFD | 16:15:05", "pubDate": "Sun, 28 May 2023 16:15:05 CDT", "active_status": "no"}, {"title": "Trash Fire", "link": "http://maps.google.com/maps?q=30.052396,-95.221852", "guid": {"@isPermaLink": "false", "#text": "30.052396,-95.221852"}, "description": "LAKEVILLE DR | HFD | 16:20:05", "pubDate": "Sun, 28 May 2023 16:20:05 CDT", "active_status": "no"}, {"title": "Dumpster on Fire", "link": "http://maps.google.com/maps?q=29.734348,-95.563852", "guid": {"@isPermaLink": "false", "#text": "29.734348,-95.563852"}, "description": "WALLINGFORD DR | HFD | 16:45:20", "pubDate": "Sun, 28 May 2023 16:45:20 CDT", "active_status": "no"}, {"title": "Fire Event", "link": "http://maps.google.com/maps?q=29.757628,-95.36448", "guid": {"@isPermaLink": "false", "#text": "29.757628,-95.36448"}, "description": "MAIN ST | HFD | 16:45:20", "pubDate": "Sun, 28 May 2023 16:45:20 CDT", "active_status": "no"}, {"title": "Trash Fire", "link": "http://maps.google.com/maps?q=29.697164,-95.443049", "guid": {"@isPermaLink": "false", "#text": "29.697164,-95.443049"}, "description": "MERRICK ST | HFD | 17:05:06", "pubDate": "Sun, 28 May 2023 17:05:06 CDT", "active_status": "no"}, {"title": "Fire Event", "link": "http://maps.google.com/maps?q=29.74989,-95.482653", "guid": {"@isPermaLink": "false", "#text": "29.74989,-95.482653"}, "description": "AUGUSTA DR | HFD | 17:15:05", "pubDate": "Sun, 28 May 2023 17:15:05 CDT", "active_status": "no"}, {"title": "Fire Event", "link": "http://maps.google.com/maps?q=29.72991,-95.575791", "guid": {"@isPermaLink": "false", "#text": "29.72991,-95.575791"}, "description": "HAYES RD | HFD | 17:30:04", "pubDate": "Sun, 28 May 2023 17:30:04 CDT", "active_status": "no"}, {"title": "Dumpster on Fire", "link": "http://maps.google.com/maps?q=29.644321,-95.502424", "guid": {"@isPermaLink": "false", "#text": "29.644321,-95.502424"}, "description": "W AIRPORT BLVD | HFD | 17:30:04", "pubDate": "Sun, 28 May 2023 17:30:04 CDT", "active_status": "no"}, {"title": "Apartment Fire", "link": "http://maps.google.com/maps?q=29.747517,-95.569026", "guid": {"@isPermaLink": "false", "#text": "29.747517,-95.569026"}, "description": "BRIAR FOREST DR | HFD | 18:00:07", "pubDate": "Sun, 28 May 2023 18:00:07 CDT", "active_status": "no"}, {"title": "Fire Event", "link": "http://maps.google.com/maps?q=29.726127,-95.491759", "guid": {"@isPermaLink": "false", "#text": "29.726127,-95.491759"}, "description": "WINDSWEPT LN | HFD | 18:10:04", "pubDate": "Sun, 28 May 2023 18:10:04 CDT", "active_status": "no"}, {"title": "Fire Event", "link": "http://maps.google.com/maps?q=29.776881,-95.398719", "guid": {"@isPermaLink": "false", "#text": "29.776881,-95.398719"}, "description": "KATY FWY OB  | HFD | 18:10:04", "pubDate": "Sun, 28 May 2023 18:10:04 CDT", "active_status": "no"}, {"title": "Fire Event", "link": "http://maps.google.com/maps?q=29.67788,-95.346717", "guid": {"@isPermaLink": "false", "#text": "29.67788,-95.346717"}, "description": "PERSHING ST | HFD | 19:25:04", "pubDate": "Sun, 28 May 2023 19:25:04 CDT", "active_status": "no"}, {"title": "Dumpster on Fire", "link": "http://maps.google.com/maps?q=29.777295,-95.374934", "guid": {"@isPermaLink": "false", "#text": "29.777295,-95.374934"}, "description": "WEBER ST | HFD | 20:00:05", "pubDate": "Sun, 28 May 2023 20:00:05 CDT", "active_status": "no"}, {"title": "Fire Event", "link": "http://maps.google.com/maps?q=29.731316,-95.464196", "guid": {"@isPermaLink": "false", "#text": "29.731316,-95.464196"}, "description": "MCCUE RD | HFD | 20:00:05", "pubDate": "Sun, 28 May 2023 20:00:05 CDT", "active_status": "no"}, {"title": "Grass Fire", "link": "http://maps.google.com/maps?q=29.863299,-95.47341", "guid": {"@isPermaLink": "false", "#text": "29.863299,-95.47341"}, "description": "W LITTLE YORK RD  | HFD | 20:10:22", "pubDate": "Sun, 28 May 2023 20:10:22 CDT", "active_status": "no"}, {"title": "Fire Event", "link": "http://maps.google.com/maps?q=29.690544,-95.548024", "guid": {"@isPermaLink": "false", "#text": "29.690544,-95.548024"}, "description": "BEECHNUT ST  | HFD | 20:10:22", "pubDate": "Sun, 28 May 2023 20:10:22 CDT", "active_status": "no"}, {"title": "Apartment Fire", "link": "http://maps.google.com/maps?q=29.841659,-95.475283", "guid": {"@isPermaLink": "false", "#text": "29.841659,-95.475283"}, "description": "DEEP FOREST DR | HFD | 20:30:21", "pubDate": "Sun, 28 May 2023 20:30:21 CDT", "active_status": "no"}, {"title": "Fire Event", "link": "http://maps.google.com/maps?q=29.845764,-95.473266", "guid": {"@isPermaLink": "false", "#text": "29.845764,-95.473266"}, "description": "ANTOINE DR | HFD | 20:30:21", "pubDate": "Sun, 28 May 2023 20:30:21 CDT", "active_status": "no"}, {"title": "House on Fire", "link": "http://maps.google.com/maps?q=29.625456,-95.285423", "guid": {"@isPermaLink": "false", "#text": "29.625456,-95.285423"}, "description": "ALMEDA GENOA RD  | HFD | 20:35:21", "pubDate": "Sun, 28 May 2023 20:35:21 CDT", "active_status": "no"}, {"title": "Building Fire", "link": "http://maps.google.com/maps?q=29.850686,-95.473328", "guid": {"@isPermaLink": "false", "#text": "29.850686,-95.473328"}, "description": "ANTOINE DR | HFD | 20:50:05", "pubDate": "Sun, 28 May 2023 20:50:05 CDT", "active_status": "no"}, {"title": "Apartment Fire", "link": "http://maps.google.com/maps?q=29.691084,-95.518348", "guid": {"@isPermaLink": "false", "#text": "29.691084,-95.518348"}, "description": "BEECHNUT ST | HFD | 20:50:05", "pubDate": "Sun, 28 May 2023 20:50:05 CDT", "active_status": "no"}, {"title": "Check for Fire", "link": "http://maps.google.com/maps?q=29.806431,-95.548902", "guid": {"@isPermaLink": "false", "#text": "29.806431,-95.548902"}, "description": "NOCTURNE LN | HFD | 20:50:05", "pubDate": "Sun, 28 May 2023 20:50:05 CDT", "active_status": "no"}, {"title": "Building Fire", "link": "http://maps.google.com/maps?q=29.850895,-95.47357", "guid": {"@isPermaLink": "false", "#text": "29.850895,-95.47357"}, "description": "N HOUSTON ROSSLYN RD | HFD | 21:00:20", "pubDate": "Sun, 28 May 2023 21:00:20 CDT", "active_status": "no"}, {"title": "Building Fire", "link": "http://maps.google.com/maps?q=29.841861,-95.384382", "guid": {"@isPermaLink": "false", "#text": "29.841861,-95.384382"}, "description": "AIRLINE DR  | HFD | 21:30:05", "pubDate": "Sun, 28 May 2023 21:30:05 CDT", "active_status": "no"}, {"title": "Fire Event", "link": "http://maps.google.com/maps?q=29.695422,-95.614656", "guid": {"@isPermaLink": "false", "#text": "29.695422,-95.614656"}, "description": "SYNOTT RD  | HFD | 21:30:05", "pubDate": "Sun, 28 May 2023 21:30:05 CDT", "active_status": "no"}, {"title": "Fire Event", "link": "http://maps.google.com/maps?q=29.597091,-95.473096", "guid": {"@isPermaLink": "false", "#text": "29.597091,-95.473096"}, "description": "SAMOA WAY | HFD | 22:15:05", "pubDate": "Sun, 28 May 2023 22:15:05 CDT", "active_status": "yes"}, {"title": "Trash Fire", "link": "http://maps.google.com/maps?q=29.700534,-95.614692", "guid": {"@isPermaLink": "false", "#text": "29.700534,-95.614692"}, "description": "GABY VIRBO DR  | HFD | 22:45:09", "pubDate": "Sun, 28 May 2023 22:45:09 CDT", "active_status": "no"}, {"title": "Fire Event", "link": "http://maps.google.com/maps?q=29.73633,-95.372814", "guid": {"@isPermaLink": "false", "#text": "29.73633,-95.372814"}, "description": "HOLMAN ST | HFD | 22:45:09", "pubDate": "Sun, 28 May 2023 22:45:09 CDT", "active_status": "no"}, {"title": "Fire Event", "link": "http://maps.google.com/maps?q=29.733848,-95.57173", "guid": {"@isPermaLink": "false", "#text": "29.733848,-95.57173"}, "description": "WILCREST DR | HFD | 22:50:06", "pubDate": "Sun, 28 May 2023 22:50:06 CDT", "active_status": "no"}, {"title": "Fire Event", "link": "http://maps.google.com/maps?q=29.740902,-95.339555", "guid": {"@isPermaLink": "false", "#text": "29.740902,-95.339555"}, "description": "DALLAS ST | HFD | 23:00:08", "pubDate": "Sun, 28 May 2023 23:00:08 CDT", "active_status": "no"}, {"title": "Fire Event", "link": "http://maps.google.com/maps?q=29.747629,-95.453919", "guid": {"@isPermaLink": "false", "#text": "29.747629,-95.453919"}, "description": "POST OAK PKWY | HFD | 23:10:05", "pubDate": "Sun, 28 May 2023 23:10:05 CDT", "active_status": "no"}, {"title": "Fire Event", "link": "http://maps.google.com/maps?q=29.765274,-95.417634", "guid": {"@isPermaLink": "false", "#text": "29.765274,-95.417634"}, "description": "REINICKE ST | HFD | 23:25:06", "pubDate": "Sun, 28 May 2023 23:25:06 CDT", "active_status": "no"}, {"title": "Motorcycle Fire", "link": "http://maps.google.com/maps?q=29.719177,-95.37756", "guid": {"@isPermaLink": "false", "#text": "29.719177,-95.37756"}, "description": "SH288IB-CALUMET ST SH 288 HWY IB | HFD | 23:30:05", "pubDate": "Sun, 28 May 2023 23:30:05 CDT", "active_status": "yes"}, {"title": "Apartment Fire", "link": "http://maps.google.com/maps?q=29.68672,-95.557509", "guid": {"@isPermaLink": "false", "#text": "29.68672,-95.557509"}, "description": "W SAM HOUSTON PKWY S | HFD | 23:35:05", "pubDate": "Sun, 28 May 2023 23:35:05 CDT", "active_status": "no"}, {"title": "Dumpster on Fire", "link": "http://maps.google.com/maps?q=29.787102,-95.521752", "guid": {"@isPermaLink": "false", "#text": "29.787102,-95.521752"}, "description": "BLALOCK RD | HFD | 23:45:05", "pubDate": "Sun, 28 May 2023 23:45:05 CDT", "active_status": "no"}]}}}